ownrepo-0.1b5.dist-info/METADATA
ownrepo-0.1b5.dist-info/WHEEL
ownrepo-0.1b5.dist-info/entry_points.txt
ownrepo-0.1b5.dist-info/top_level.txt
ownrepo-0.1b5.dist-info/DESCRIPTION.rst
ownrepo-0.1b5.dist-info/RECORD
ownrepo-0.1b5.dist-info/metadata.json
ownrepo/repositories.py
ownrepo/utils.py
ownrepo/upgrader.py
ownrepo/schema.sql
ownrepo/web.py
ownrepo/db.py
ownrepo/__main__.py
ownrepo/__init__.py
ownrepo/authentication.py
ownrepo/templates/simple_package.html
ownrepo/templates/packages_list.html
ownrepo/templates/layout.html
ownrepo/templates/login_failed.html
ownrepo/templates/package.html
ownrepo/templates/simple_repo.html
ownrepo/templates/repo.html
ownrepo/templates/.layout.html.swp
ownrepo/templates/release.html
ownrepo/templates/not_found.html
ownrepo/templates/home.html
ownrepo/static/.ownrepo.css.swp
ownrepo/static/ownrepo.css
