Metadata-Version: 2.0
Name: ownrepo
Version: 0.1b5
Summary: Simple, easy-to-setup private Python packages repository
Home-page: http://ownrepo.pietroalbini.io/
Author: Pietro Albini
Author-email: pietro@pietroalbini.io
License: MIT
Platform: UNKNOWN
Classifier: Development Status :: 4 - Beta
Classifier: Environment :: Web Environment
Classifier: Environment :: Console
Classifier: Framework :: Flask
Classifier: Intended Audience :: Developers
Classifier: Intended Audience :: System Administrators
Classifier: License :: OSI Approved :: MIT License
Classifier: Natural Language :: English
Classifier: Operating System :: POSIX :: Linux
Classifier: Programming Language :: Python :: 3
Classifier: Programming Language :: Python :: 3.3
Classifier: Programming Language :: Python :: 3.4
Classifier: Programming Language :: Python :: 3 :: Only
Classifier: Topic :: Software Development
Classifier: Topic :: System :: Archiving :: Packaging
Classifier: Topic :: System :: Software Distribution
Requires-Dist: flask
Requires-Dist: pyyaml
Requires-Dist: setuptools
Requires-Dist: click
Requires-Dist: gunicorn
